fredquery/__about__.py
fredquery/__init__.py
fredquery/aa2csv.py
fredquery/aa2html.py
fredquery/fredcategories.py
fredquery/fredplot.py
fredquery/fredplotseries.py
fredquery/fredreleases.py
fredquery/fredseries.py
fredquery/fredsources.py
fredquery/fredtags.py
fredquery/query.py
fredquery/xmlstr2aa.py
fredquery/.ipynb_checkpoints/Ploteg0-checkpoint.ipynb
fredquery/.ipynb_checkpoints/Untitled-checkpoint.ipynb
fredquery-0.0.56.dist-info/METADATA
fredquery-0.0.56.dist-info/WHEEL
fredquery-0.0.56.dist-info/entry_points.txt
fredquery-0.0.56.dist-info/licenses/LICENSE.txt
fredquery-0.0.56.dist-info/RECORD
