Metadata-Version: 2.4
Name: fredquery
Version: 0.0.56
Summary: Downloads various stlouisfed.org FRED files to CSV files and creates plots based on category, release, series, source, or tag
Project-URL: Documentation, https://github.com/dfwcnj/fredquery#readme
Project-URL: Issues, https://github.com/dfwcnj/fredquery/issues
Project-URL: Source, https://github.com/dfwcnj/fredquery
Author-email: Don Caldwell <dfwcnj@gmail.com>
License-Expression: MIT
License-File: LICENSE.txt
Classifier: Development Status :: 4 - Beta
Classifier: Programming Language :: Python
Classifier: Programming Language :: Python :: 3.8
Classifier: Programming Language :: Python :: 3.9
Classifier: Programming Language :: Python :: 3.10
Classifier: Programming Language :: Python :: 3.11
Classifier: Programming Language :: Python :: 3.12
Classifier: Programming Language :: Python :: Implementation :: CPython
Classifier: Programming Language :: Python :: Implementation :: PyPy
Requires-Python: >=3.8
